hackmudChatAPI/__init__.py
hackmudChatAPI/__main__.py
hackmudChatAPI/hackmudChatAPI.py
hackmudChatAPI/package_data.py
hackmudChatAPI/types.py
hackmudchatapi-0.0.20.2.dist-info/licenses/LICENSE
hackmudchatapi-0.0.20.2.dist-info/WHEEL
hackmudchatapi-0.0.20.2.dist-info/METADATA
hackmudchatapi-0.0.20.2.dist-info/RECORD
